Verilog_codes/8bitshiftregister/SR_SISO.v
module DFF(d,clk,reset,q);
input clk, reset;
input wire d;
output reg q;

always@(negedge clk or posedge reset)
begin
	if(reset)
 		q <= 1'b0;
	else
		q <= d;
end

endmodule


module SR_SISO(d,clk,reset,q);

input d, clk, reset;
output q;

wire w1, w2, w3,w4,w5,w6,w7;

DFF dff_1(d, clk, reset, w1);
DFF dff_2(w1, clk, reset, w2);
DFF dff_3(w2, clk, reset, w3);
DFF dff_4(w3, clk, reset, w4);
DFF dff_5(w4, clk, reset, w5);
DFF dff_6(w5, clk, reset, w6);
DFF dff_7(w6, clk, reset, w7);
DFF dff_8(w7, clk, reset, q);

endmodule

Verilog_codes/8bitshiftregister/PISO/SR_PISO.v
`include "DFF.v"

module SR_PISO(d,clk,reset,q, write_check);

input [4:1]d;
input write_check;
input clk, reset;
output q;

wire w[3:1];

wire outputs[3:1];

assign w[1] = (write_check&d[1]) | ((~write_check)&outputs[1]);
assign w[2] = (write_check&d[2]) | ((~write_check)&outputs[2]);
assign w[3] = (write_check&d[3]) | ((~write_check)&outputs[3]);

DFF dff_1(d[1], clk, reset, outputs[1]);
DFF dff_2(w[1], clk, reset, outputs[2]);
DFF dff_3(w[2], clk, reset, outputs[3]);
DFF dff_4(w[3], clk, reset, q);

endmodule

module SR_PISO_eight(d,clk,reset,q, write_check);

input [8:1]d;
input write_check;
input clk, reset;
output q;

wire [4:1]w;

wire outputs[4:1];

assign w[1] = (write_check&d[5]) | ((~write_check)&outputs[1]);
assign w[2] = (write_check&d[6]) | ((~write_check)&outputs[2]);
assign w[3] = (write_check&d[7]) | ((~write_check)&outputs[3]);
assign w[4] = (write_check&d[8]) | ((~write_check)&outputs[4]);


SR_PISO dff_1(d[4:1], clk, reset, outputs[4],write_check);
SR_PISO dff_2(w[4:1], clk, reset, q,write_check);

endmodule

Verilog_codes/8bitshiftregister/PISO/SR_PISO_tb.v
`include "SR_PISO.v"

module SR_PISO_tb;

reg clk, reset, write;
wire q;

reg [8:1] inp;

initial
	begin
		$dumpfile("SR_PISO_tb.vcd");
		$dumpvars(0, SR_PISO_tb);
	end

SR_PISO_eight srPISO(inp, clk, reset, q, write);


initial
	begin
		reset=0;
		clk =0;
		   write = 1;inp = 8'b00000000;
		#5 write = 1;inp = 8'b00100010;
		#5 write = 1;inp = 8'b00011110;
		#5 write = 1;inp = 8'b10100001;
		#5 write = 1;inp = 8'b00001010;
		#5 write = 1;inp = 8'b01101111;
		#5 write = 1;inp = 8'b00010000;
		#5 write = 1;inp = 8'b00101110;
		#5 write = 1;inp = 8'b00000011;
		#5 write = 1;inp = 8'b00100100;
		#5 write = 1;inp = 8'b00011000;
	end

always #5  
	clk =  ! clk; 

initial
	$monitor($time, ": clk=%b, rst=%b, inp=%b, q=%b\n", clk, reset, inp, q);

initial
	#60 $finish;

endmodule

Verilog_codes/8bitshiftregister/PISO/SR_PISO_tb.vcd
$date
	Wed Aug 26 00:44:20 2020
$end
$version
	Icarus Verilog
$end
$timescale
	1s
$end
$scope module SR_PISO_tb $end
$var wire 1 ! q $end
$var reg 1 " clk $end
$var reg 8 # inp [8:1] $end
$var reg 1 $ reset $end
$var reg 1 % write $end
$scope module srPISO $end
$var wire 1 " clk $end
$var wire 8 & d [8:1] $end
$var wire 1 $ reset $end
$var wire 1 % write_check $end
$var wire 4 ' w [4:1] $end
$var wire 1 ! q $end
$scope module dff_1 $end
$var wire 1 " clk $end
$var wire 4 ( d [4:1] $end
$var wire 1 $ reset $end
$var wire 1 % write_check $end
$var wire 1 ) q $end
$scope module dff_1 $end
$var wire 1 " clk $end
$var wire 1 * d $end
$var wire 1 $ reset $end
$var reg 1 + q $end
$upscope $end
$scope module dff_2 $end
$var wire 1 " clk $end
$var wire 1 , d $end
$var wire 1 $ reset $end
$var reg 1 - q $end
$upscope $end
$scope module dff_3 $end
$var wire 1 " clk $end
$var wire 1 . d $end
$var wire 1 $ reset $end
$var reg 1 / q $end
$upscope $end
$scope module dff_4 $end
$var wire 1 " clk $end
$var wire 1 0 d $end
$var wire 1 $ reset $end
$var reg 1 ) q $end
$upscope $end
$upscope $end
$scope module dff_2 $end
$var wire 1 " clk $end
$var wire 4 1 d [4:1] $end
$var wire 1 $ reset $end
$var wire 1 % write_check $end
$var wire 1 ! q $end
$scope module dff_1 $end
$var wire 1 " clk $end
$var wire 1 2 d $end
$var wire 1 $ reset $end
$var reg 1 3 q $end
$upscope $end
$scope module dff_2 $end
$var wire 1 " clk $end
$var wire 1 4 d $end
$var wire 1 $ reset $end
$var reg 1 5 q $end
$upscope $end
$scope module dff_3 $end
$var wire 1 " clk $end
$var wire 1 6 d $end
$var wire 1 $ reset $end
$var reg 1 7 q $end
$upscope $end
$scope module dff_4 $end
$var wire 1 " clk $end
$var wire 1 8 d $end
$var wire 1 $ reset $end
$var reg 1 ! q $end
$upscope $end
$upscope $end
$upscope $end
$upscope $end
$enddefinitions $end
#0
$dumpvars
08
x7
06
x5
04
x3
02
b0 1
00
x/
0.
x-
0,
x+
0*
x)
b0 (
b0 '
b0 &
1%
0$
b0 #
0"
x!
$end
#5
16
1.
b10 '
b10 1
b10 (
1"
b100010 #
b100010 &
#10
0!
17
05
03
0)
1/
0-
0+
14
06
12
10
b1 '
b1 1
b1110 (
0"
b11110 #
b11110 &
#15
04
16
02
1,
0.
00
b1010 '
b1010 1
1*
b1 (
1"
b10100001 #
b10100001 &
#20
1+
1-
0/
06
0,
1.
b0 '
b0 1
0*
b1010 (
0"
b1010 #
b1010 &
#25
16
18
1,
10
b110 '
b110 1
1*
b1111 (
1"
b1101111 #
b1101111 &
#30
1!
1)
1/
14
06
08
12
0,
0.
00
b1 '
b1 1
0*
b0 (
0"
b10000 #
b10000 &
#35
04
16
02
1.
10
b10 '
b10 1
b1110 (
1"
b101110 #
b101110 &
#40
0+
0-
0!
06
1,
00
b0 '
b0 1
1*
b11 (
0"
b11 #
b11 &
#45
16
0,
0.
10
b10 '
b10 1
0*
b100 (
1"
b100100 #
b100100 &
#50
0/
14
06
12
00
b1 '
b1 1
b1000 (
0"
b11000 #
b11000 &
#55
1"
#60
0)
13
15
07
0"
