Verilog_codes/8bitshiftregister/SR_SISO.v
module DFF(d,clk,reset,q);
input clk, reset;
input wire d;
output reg q;

always@(negedge clk or posedge reset)
begin
	if(reset)
 		q <= 1'b0;
	else
		q <= d;
end

endmodule


module SR_SISO(d,clk,reset,q);

input d, clk, reset;
output q;

wire w1, w2, w3,w4,w5,w6,w7;

DFF dff_1(d, clk, reset, w1);
DFF dff_2(w1, clk, reset, w2);
DFF dff_3(w2, clk, reset, w3);
DFF dff_4(w3, clk, reset, w4);
DFF dff_5(w4, clk, reset, w5);
DFF dff_6(w5, clk, reset, w6);
DFF dff_7(w6, clk, reset, w7);
DFF dff_8(w7, clk, reset, q);

endmodule

Verilog_codes/8bitshiftregister/USR/USR.v
`include "DFF.v"

module USR(inputs,serialin,clk,reset,outputs, select);

input [4:1] inputs;
input serialin;
input [2:1]select;
input clk, reset;

wire [4:1]w;

output [4:1]outputs;

assign w[1] = ((~select[2])&(~select[1])&outputs[1]) | (select[2]&(~select[1])&outputs[2]) | ((~select[2])&select[1]&serialin) 		 | (select[2]&select[1]&inputs[1]);
assign w[2] = ((~select[2])&(~select[1])&outputs[2]) | (select[2]&(~select[1])&outputs[3]) | ((~select[2])&select[1]&outputs[1]) | (select[2]&select[1]&inputs[2]);
assign w[3] = ((~select[2])&(~select[1])&outputs[3]) | (select[2]&(~select[1])&outputs[4]) | ((~select[2])&select[1]&outputs[2]) | (select[2]&select[1]&inputs[3]);
assign w[4] = ((~select[2])&(~select[1])&outputs[4]) | (select[2]&(~select[1])&serialin) 		   | ((~select[2])&select[1]&outputs[3]) | (select[2]&select[1]&inputs[4]);

DFF dff_1(w[1], clk, reset, outputs[1]);
DFF dff_2(w[2], clk, reset, outputs[2]);
DFF dff_3(w[3], clk, reset, outputs[3]);
DFF dff_4(w[4], clk, reset, outputs[4]);

endmodule



module USR_eight(inputs,serialin,clk,reset,outputs, select);

input [8:1]inputs;
input serialin;
input [2:1]select;
input clk, reset;

wire [4:1]w;

output [8:1]outputs;

assign w[1] = ((~select[2])&(~select[1])&outputs[1]) | (select[2]&(~select[1])&outputs[2]) | ((~select[2])&select[1]&serialin) 		 | (select[2]&select[1]&inputs[5]);
assign w[2] = ((~select[2])&(~select[1])&outputs[2]) | (select[2]&(~select[1])&outputs[3]) | ((~select[2])&select[1]&outputs[1]) | (select[2]&select[1]&inputs[6]);
assign w[3] = ((~select[2])&(~select[1])&outputs[3]) | (select[2]&(~select[1])&outputs[4]) | ((~select[2])&select[1]&outputs[2]) | (select[2]&select[1]&inputs[7]);
assign w[4] = ((~select[2])&(~select[1])&outputs[4]) | (select[2]&(~select[1])&serialin) 		   | ((~select[2])&select[1]&outputs[3]) | (select[2]&select[1]&inputs[8]);

USR u1(inputs[4:1],serialin,clk,reset,outputs[4:1],select);
USR u2(w[4:1],serialin,clk,reset,outputs[8:5],select);
endmodule

Verilog_codes/8bitshiftregister/USR/USR_tb.v
`include "USR.v"

module USR_tb;

reg clk, reset;
reg [2:1]select;		// 00 - output		01 - Left Shift		10 - Right Shift 		11 - Write
wire [8:1] q;
reg serialin;

reg [8:1] inp;

initial
	begin
		$dumpfile("USR_tb.vcd");
		$dumpvars(0, USR_tb);
	end

USR_eight srPIPO(inp, serialin, clk, reset, q, select);


initial
	begin
		reset=0;
		clk =0;
		select = 2'b11;
		serialin = 1'b0;

		inp = 8'b10111001;
		#10 select = 2'b00;
		
		#10 select = 2'b11;inp = 8'b11110000;
		#10 select = 2'b01;
		#10 select = 2'b01;
		#10 serialin = 1'b1;select = 2'b01;
		#10 select = 2'b01;
		#10 select = 2'b11;inp = 8'b11110000;
		#10 select = 2'b10;
		#10 select = 2'b10;
		#10 select = 2'b10;
		#10 select = 2'b10;
		#10 select = 2'b00;
		
	end

always #5  
	clk =  ! clk; 

initial
	$monitor($time, ": clk=%b, rst=%b, select=%b, inp=%b, q=%b\n", clk, reset, select, inp, q);

initial
	#100 $finish;

endmodule

Verilog_codes/8bitshiftregister/USR/USR_tb.vcd
$date
	Wed Aug 26 01:05:35 2020
$end
$version
	Icarus Verilog
$end
$timescale
	1s
$end
$scope module USR_tb $end
$var wire 8 ! q [8:1] $end
$var reg 1 " clk $end
$var reg 8 # inp [8:1] $end
$var reg 1 $ reset $end
$var reg 2 % select [2:1] $end
$var reg 1 & serialin $end
$scope module srPIPO $end
$var wire 1 " clk $end
$var wire 8 ' inputs [8:1] $end
$var wire 1 $ reset $end
$var wire 2 ( select [2:1] $end
$var wire 1 & serialin $end
$var wire 4 ) w [4:1] $end
$var wire 8 * outputs [8:1] $end
$scope module u1 $end
$var wire 1 " clk $end
$var wire 4 + inputs [4:1] $end
$var wire 1 $ reset $end
$var wire 2 , select [2:1] $end
$var wire 1 & serialin $end
$var wire 4 - w [4:1] $end
$var wire 4 . outputs [4:1] $end
$scope module dff_1 $end
$var wire 1 " clk $end
$var wire 1 / d $end
$var wire 1 $ reset $end
$var reg 1 0 q $end
$upscope $end
$scope module dff_2 $end
$var wire 1 " clk $end
$var wire 1 1 d $end
$var wire 1 $ reset $end
$var reg 1 2 q $end
$upscope $end
$scope module dff_3 $end
$var wire 1 " clk $end
$var wire 1 3 d $end
$var wire 1 $ reset $end
$var reg 1 4 q $end
$upscope $end
$scope module dff_4 $end
$var wire 1 " clk $end
$var wire 1 5 d $end
$var wire 1 $ reset $end
$var reg 1 6 q $end
$upscope $end
$upscope $end
$scope module u2 $end
$var wire 1 " clk $end
$var wire 4 7 inputs [4:1] $end
$var wire 1 $ reset $end
$var wire 2 8 select [2:1] $end
$var wire 1 & serialin $end
$var wire 4 9 w [4:1] $end
$var wire 4 : outputs [4:1] $end
$scope module dff_1 $end
$var wire 1 " clk $end
$var wire 1 ; d $end
$var wire 1 $ reset $end
$var reg 1 < q $end
$upscope $end
$scope module dff_2 $end
$var wire 1 " clk $end
$var wire 1 = d $end
$var wire 1 $ reset $end
$var reg 1 > q $end
$upscope $end
$scope module dff_3 $end
$var wire 1 " clk $end
$var wire 1 ? d $end
$var wire 1 $ reset $end
$var reg 1 @ q $end
$upscope $end
$scope module dff_4 $end
$var wire 1 " clk $end
$var wire 1 A d $end
$var wire 1 $ reset $end
$var reg 1 B q $end
$upscope $end
$upscope $end
$upscope $end
$upscope $end
$enddefinitions $end
#0
$dumpvars
xB
1A
x@
0?
x>
1=
x<
1;
bx :
b1011 9
b11 8
b1011 7
x6
15
x4
03
x2
01
x0
1/
bx .
b1001 -
b11 ,
b1001 +
bx *
b1011 )
b11 (
b10111001 '
0&
b11 %
0$
b10111001 #
0"
bx !
$end
#5
1"
#10
1B
0@
1>
b1011 :
1<
16
04
02
b10111001 !
b10111001 *
b1001 .
10
01
03
0?
1/
15
1;
1=
1A
b1001 )
b1001 7
b1001 -
b1011 9
0"
b0 %
b0 (
b0 ,
b0 8
#15
1"
#20
0/
05
01
1?
b0 -
b1111 9
b1111 )
b1111 7
b0 +
0"
b11110000 #
b11110000 '
b11 %
b11 (
b11 ,
b11 8
#25
1"
#30
b1111 :
1@
06
b11110000 !
b11110000 *
b0 .
00
01
b0 -
0;
1=
1?
1A
b0 )
b0 7
b1110 9
0"
b1 %
b1 (
b1 ,
b1 8
#35
1"
#40
0=
b1100 9
b11100000 !
b11100000 *
b1110 :
0<
0"
#45
1"
#50
0?
b11000000 !
b11000000 *
b1100 :
0>
1/
1;
b1 )
b1 7
b1 -
b1001 9
0"
1&
#55
1"
#60
11
1=
0A
b11 -
b11 )
b11 7
b11 9
b1 .
10
1<
b10010001 !
b10010001 *
b1001 :
0@
0"
#65
1"
#70
0B
b11 :
1>
b110011 !
b110011 *
b11 .
12
1?
1A
b1111 9
0/
01
b0 -
b1111 )
b1111 7
0"
b11 %
b11 (
b11 ,
b11 8
#75
1"
#80
00
b0 .
02
1@
b11110000 !
b11110000 *
b1111 :
1B
0/
15
b1000 -
1;
1=
1?
1A
b1000 )
b1000 7
b1111 9
0"
b10 %
b10 (
b10 ,
b10 8
#85
1"
#90
13
b1100 -
b1100 )
b1100 7
b11111000 !
b11111000 *
b1000 .
16
0"
#95
1"
#100
11
b1110 -
b1110 )
b1110 7
b11111100 !
b11111100 *
b1100 .
14
0"
