Verilog_codes/8bitshiftregister/uSR.v
//D flip flop
module dFF(q,D,clk);
	output q;
	input D, clk;

	wire o0_0,o0_1,o0_2,o0_3;
	nand n0_0(o0_0,o0_1,o0_3);
	nand n0_1(o0_1,o0_0,clk);
	nand no_2(o0_2,o0_1,o0_3,clk);
	nand no_3(o0_3,o0_2,D);
	wire Qn;
	nand n1_0(q,o0_1,Qn);
	nand n1_1(Qn,o0_2,q);

endmodule

// a 4X1 MUX to perform operation according to user input, 00- do nothing, 01- right shift, 10- left shift, 11- write;
module mux_4to1 (out,i0,i1,i2,i3,select);

	input i0,i1,i2,i3;
	input[1:0] select;
	output out;

	wire s0_not, s1_not;
	not n0(s0_not,select[0]);
	not n1(s1_not,select[1]);
	wire a0,a1,a2,a3;
	and a0_0(a0,s1_not,s0_not,i0);
	and a0_1(a1,s1_not,select[0],i1);
	and a0_2(a2,select[1],s0_not,i2);
	and a0_3(a3,select[1],select[0],i3);
	or o0_0(out,a0,a1,a2,a3);

endmodule 

//Universal shift register for 4 bits
module fourBit(out,pload,lftin,rghtin,select,clk);


	output[3:0] out;
	input[3:0] pload;
	input lftin,rghtin;
	input[1:0] select;
	input clk;

	wire o0,o1,o2,o3;						

	dFF df3(out[3],o3,clk);
	dFF df2(out[2],o2,clk);
	dFF df1(out[1],o1,clk);
	dFF df0(out[0],o0,clk);

	mux_4to1 mx3(o3,out[3],rghtin,out[2],pload[3],select);
	mux_4to1 mx2(o2,out[2],out[3],out[1],pload[2],select);
	mux_4to1 mx1(o1,out[1],out[2],out[0],pload[1],select);
	mux_4to1 mx0(o0,out[0],out[1],lftin,pload[0],select);

endmodule

//universal shift register in 8 bits using bottom up approach
module eightBit(out,pload,lftin,rghtin,select,clk);


	output[7:0] out;
	input[7:0] pload;
	input lftin,rghtin;
	input[1:0] select;
	input clk;

	fourBit fb_usr0(out[7:4],pload[7:4],out[3],rghtin,select,clk);
	fourBit fb_usr1(out[3:0],pload[3:0],lftin,out[4],select,clk);

endmodule

Verilog_codes/8bitshiftregister/USR_tb.v
`include "uSR.v"

module top;

	wire[7:0] out;
	reg[7:0] pload;
	reg lftin,rghtin;
	reg[1:0] select;
	reg clk;

	eightBit usr0(out,pload,lftin,rghtin,select,clk);

	always #5 clk = ~clk;

	initial
	begin
		$monitor($time," SelectInputs = %2b ---- Parallelload = %8b --- lftin = %b, rghtin = %b, -- out = %8b",select,pload,lftin,rghtin,out);
	end

	initial
	begin	
		clk =0;select = 2'b11; pload = 8'b0000_0000; lftin = 1'b0; rghtin = 1'b0; 

		#10 select = 2'b11; pload = 8'b0001_0001;

		#10 select = 2'b11; pload = 8'b1111_0000;

		#10 select = 2'b11; pload = 8'b1010_0101; 

		#10 select = 2'b11; pload = 8'b1111_0000;

		#10 select = 2'b01; rghtin = 1'b0; 

		#10 select = 2'b01; rghtin = 1'b0; 

		#10 select = 2'b01; rghtin = 1'b0; 

		#10 select = 2'b01; rghtin = 1'b0; 

		#10 select = 2'b01; rghtin = 1'b0; 

		#10 select = 2'b10; lftin = 1'b1;

		#10 select = 2'b10; lftin = 1'b1;

		#10 select = 2'b10; lftin = 1'b1;

		#10 select = 2'b10; lftin = 1'b1;

		#10 select = 2'b10; lftin = 1'b1;

	end
	initial
	#140 $finish;
	initial
	begin
	  $dumpfile("USR.vcd");      
      $dumpvars;
    end                        
    
endmodule

Verilog_codes/8bitshiftregister/USR.vcd
$date
	Thu Aug 27 13:30:10 2020
$end
$version
	Icarus Verilog
$end
$timescale
	1s
$end
$scope module top $end
$var wire 8 ! out [7:0] $end
$var reg 1 " clk $end
$var reg 1 # lftin $end
$var reg 8 $ pload [7:0] $end
$var reg 1 % rghtin $end
$var reg 2 & select [1:0] $end
$scope module usr0 $end
$var wire 1 " clk $end
$var wire 1 # lftin $end
$var wire 8 ' pload [7:0] $end
$var wire 1 % rghtin $end
$var wire 2 ( select [1:0] $end
$var wire 8 ) out [7:0] $end
$scope module fb_usr0 $end
$var wire 1 " clk $end
$var wire 1 * lftin $end
$var wire 4 + pload [3:0] $end
$var wire 1 % rghtin $end
$var wire 2 , select [1:0] $end
$var wire 4 - out [3:0] $end
$var wire 1 . o3 $end
$var wire 1 / o2 $end
$var wire 1 0 o1 $end
$var wire 1 1 o0 $end
$scope module df0 $end
$var wire 1 2 Qn $end
$var wire 1 " clk $end
$var wire 1 3 o0_0 $end
$var wire 1 4 o0_1 $end
$var wire 1 5 o0_2 $end
$var wire 1 6 o0_3 $end
$var wire 1 7 q $end
$var wire 1 1 D $end
$upscope $end
$scope module df1 $end
$var wire 1 8 Qn $end
$var wire 1 " clk $end
$var wire 1 9 o0_0 $end
$var wire 1 : o0_1 $end
$var wire 1 ; o0_2 $end
$var wire 1 < o0_3 $end
$var wire 1 = q $end
$var wire 1 0 D $end
$upscope $end
$scope module df2 $end
$var wire 1 > Qn $end
$var wire 1 " clk $end
$var wire 1 ? o0_0 $end
$var wire 1 @ o0_1 $end
$var wire 1 A o0_2 $end
$var wire 1 B o0_3 $end
$var wire 1 C q $end
$var wire 1 / D $end
$upscope $end
$scope module df3 $end
$var wire 1 D Qn $end
$var wire 1 " clk $end
$var wire 1 E o0_0 $end
$var wire 1 F o0_1 $end
$var wire 1 G o0_2 $end
$var wire 1 H o0_3 $end
$var wire 1 I q $end
$var wire 1 . D $end
$upscope $end
$scope module mx0 $end
$var wire 1 J a0 $end
$var wire 1 K a1 $end
$var wire 1 L a2 $end
$var wire 1 M a3 $end
$var wire 1 N i0 $end
$var wire 1 O i1 $end
$var wire 1 * i2 $end
$var wire 1 P i3 $end
$var wire 1 1 out $end
$var wire 1 Q s0_not $end
$var wire 1 R s1_not $end
$var wire 2 S select [1:0] $end
$upscope $end
$scope module mx1 $end
$var wire 1 T a0 $end
$var wire 1 U a1 $end
$var wire 1 V a2 $end
$var wire 1 W a3 $end
$var wire 1 X i0 $end
$var wire 1 Y i1 $end
$var wire 1 Z i2 $end
$var wire 1 [ i3 $end
$var wire 1 0 out $end
$var wire 1 \ s0_not $end
$var wire 1 ] s1_not $end
$var wire 2 ^ select [1:0] $end
$upscope $end
$scope module mx2 $end
$var wire 1 _ a0 $end
$var wire 1 ` a1 $end
$var wire 1 a a2 $end
$var wire 1 b a3 $end
$var wire 1 c i0 $end
$var wire 1 d i1 $end
$var wire 1 e i2 $end
$var wire 1 f i3 $end
$var wire 1 / out $end
$var wire 1 g s0_not $end
$var wire 1 h s1_not $end
$var wire 2 i select [1:0] $end
$upscope $end
$scope module mx3 $end
$var wire 1 j a0 $end
$var wire 1 k a1 $end
$var wire 1 l a2 $end
$var wire 1 m a3 $end
$var wire 1 n i0 $end
$var wire 1 % i1 $end
$var wire 1 o i2 $end
$var wire 1 p i3 $end
$var wire 1 . out $end
$var wire 1 q s0_not $end
$var wire 1 r s1_not $end
$var wire 2 s select [1:0] $end
$upscope $end
$upscope $end
$scope module fb_usr1 $end
$var wire 1 " clk $end
$var wire 1 # lftin $end
$var wire 4 t pload [3:0] $end
$var wire 1 u rghtin $end
$var wire 2 v select [1:0] $end
$var wire 4 w out [3:0] $end
$var wire 1 x o3 $end
$var wire 1 y o2 $end
$var wire 1 z o1 $end
$var wire 1 { o0 $end
$scope module df0 $end
$var wire 1 | Qn $end
$var wire 1 " clk $end
$var wire 1 } o0_0 $end
$var wire 1 ~ o0_1 $end
$var wire 1 !" o0_2 $end
$var wire 1 "" o0_3 $end
$var wire 1 #" q $end
$var wire 1 { D $end
$upscope $end
$scope module df1 $end
$var wire 1 $" Qn $end
$var wire 1 " clk $end
$var wire 1 %" o0_0 $end
$var wire 1 &" o0_1 $end
$var wire 1 '" o0_2 $end
$var wire 1 (" o0_3 $end
$var wire 1 )" q $end
$var wire 1 z D $end
$upscope $end
$scope module df2 $end
$var wire 1 *" Qn $end
$var wire 1 " clk $end
$var wire 1 +" o0_0 $end
$var wire 1 ," o0_1 $end
$var wire 1 -" o0_2 $end
$var wire 1 ." o0_3 $end
$var wire 1 /" q $end
$var wire 1 y D $end
$upscope $end
$scope module df3 $end
$var wire 1 0" Qn $end
$var wire 1 " clk $end
$var wire 1 1" o0_0 $end
$var wire 1 2" o0_1 $end
$var wire 1 3" o0_2 $end
$var wire 1 4" o0_3 $end
$var wire 1 5" q $end
$var wire 1 x D $end
$upscope $end
$scope module mx0 $end
$var wire 1 6" a0 $end
$var wire 1 7" a1 $end
$var wire 1 8" a2 $end
$var wire 1 9" a3 $end
$var wire 1 :" i0 $end
$var wire 1 ;" i1 $end
$var wire 1 # i2 $end
$var wire 1 <" i3 $end
$var wire 1 { out $end
$var wire 1 =" s0_not $end
$var wire 1 >" s1_not $end
$var wire 2 ?" select [1:0] $end
$upscope $end
$scope module mx1 $end
$var wire 1 @" a0 $end
$var wire 1 A" a1 $end
$var wire 1 B" a2 $end
$var wire 1 C" a3 $end
$var wire 1 D" i0 $end
$var wire 1 E" i1 $end
$var wire 1 F" i2 $end
$var wire 1 G" i3 $end
$var wire 1 z out $end
$var wire 1 H" s0_not $end
$var wire 1 I" s1_not $end
$var wire 2 J" select [1:0] $end
$upscope $end
$scope module mx2 $end
$var wire 1 K" a0 $end
$var wire 1 L" a1 $end
$var wire 1 M" a2 $end
$var wire 1 N" a3 $end
$var wire 1 O" i0 $end
$var wire 1 P" i1 $end
$var wire 1 Q" i2 $end
$var wire 1 R" i3 $end
$var wire 1 y out $end
$var wire 1 S" s0_not $end
$var wire 1 T" s1_not $end
$var wire 2 U" select [1:0] $end
$upscope $end
$scope module mx3 $end
$var wire 1 V" a0 $end
$var wire 1 W" a1 $end
$var wire 1 X" a2 $end
$var wire 1 Y" a3 $end
$var wire 1 Z" i0 $end
$var wire 1 u i1 $end
$var wire 1 [" i2 $end
$var wire 1 \" i3 $end
$var wire 1 x out $end
$var wire 1 ]" s0_not $end
$var wire 1 ^" s1_not $end
$var wire 2 _" select [1:0] $end
$upscope $end
$upscope $end
$upscope $end
$upscope $end
$enddefinitions $end
#0
$dumpvars
b11 _"
0^"
0]"
0\"
x["
xZ"
0Y"
0X"
0W"
0V"
b11 U"
0T"
0S"
0R"
xQ"
xP"
xO"
0N"
0M"
0L"
0K"
b11 J"
0I"
0H"
0G"
xF"
xE"
xD"
0C"
0B"
0A"
0@"
b11 ?"
0>"
0="
0<"
x;"
x:"
09"
08"
07"
06"
x5"
14"
13"
12"
01"
x0"
x/"
1."
1-"
1,"
0+"
x*"
x)"
1("
1'"
1&"
0%"
x$"
x#"
1""
1!"
1~
0}
x|
0{
0z
0y
0x
bx w
b11 v
xu
b0 t
b11 s
0r
0q
0p
xo
xn
0m
0l
0k
0j
b11 i
0h
0g
0f
xe
xd
xc
0b
0a
0`
0_
b11 ^
0]
0\
0[
xZ
xY
xX
0W
0V
0U
0T
b11 S
0R
0Q
0P
xO
xN
0M
0L
0K
0J
xI
1H
1G
1F
0E
xD
xC
1B
1A
1@
0?
x>
x=
1<
1;
1:
09
x8
x7
16
15
14
03
x2
01
00
0/
0.
bx -
b11 ,
b0 +
x*
bx )
b11 (
b0 '
b11 &
0%
b0 $
0#
0"
bx !
$end
#5
0Z
0N
0u
0e
0X
0O
0o
0c
0Y
0n
0d
0F"
0:"
0Q"
0D"
0;"
0["
0O"
0E"
0Z"
0P"
0*
07
0=
0C
b0 -
0I
0#"
0)"
0/"
b0 !
b0 )
b0 w
05"
12
18
1>
1D
1|
1$"
1*"
10"
05
0;
0A
0G
0!"
0'"
0-"
03"
1"
#10
13
1}
06
0""
11
1{
1M
19"
1P
1<"
15
1;
1A
1G
1!"
1'"
1-"
13"
b1 +
b1 t
0"
b10001 $
b10001 '
#15
02
1Z
1N
1u
0|
1F"
1:"
b1 -
17
b10001 !
b10001 )
b1 w
1#"
04
0;
0A
0G
0~
0'"
0-"
03"
1"
#20
1E
1?
19
0}
0H
0B
0<
1""
1.
1/
10
0{
1m
1b
1W
09"
1p
1f
1[
0<"
14
1;
1A
1G
1~
1'"
1-"
13"
b1111 +
b0 t
0"
b11110000 $
b11110000 '
#25
0F"
0:"
08
1e
1X
1O
0>
1o
1c
1Y
0D
1n
1d
b0 w
0#"
1=
1C
b11110000 !
b11110000 )
b1111 -
1I
1|
04
0:
0@
0F
0!"
0'"
0-"
03"
1"
#30
0?
03
1+"
1}
1B
16
0."
0""
0/
01
1y
1{
0b
0M
1N"
19"
0f
0P
1R"
1<"
14
1:
1@
1F
1!"
1'"
1-"
13"
b1010 +
b101 t
0"
b10100101 $
b10100101 '
#35
0Z
0N
0u
0o
0c
0Y
07
b1010 -
0C
0|
1F"
1:"
0*"
1["
1O"
1E"
12
1>
1#"
b10100101 !
b10100101 )
b101 w
1/"
05
0:
0A
0F
0~
0'"
0,"
03"
1"
#40
1?
13
0+"
0}
0B
06
1."
1""
1/
11
0y
0{
1b
1M
0N"
09"
1f
1P
0R"
0<"
15
1:
1A
1F
1~
1'"
1,"
13"
b1111 +
b0 t
0"
b11110000 $
b11110000 '
#45
0F"
0:"
0["
0O"
0E"
02
1Z
1N
1u
0>
1o
1c
1Y
0#"
b0 w
0/"
17
b11110000 !
b11110000 )
b1111 -
1C
1|
1*"
04
0:
0@
0F
0!"
0'"
0-"
03"
1"
#50
11"
13
19
1?
0E
04"
06
0<
0B
1H
1x
1K
11
1U
10
1`
1/
0.
1W"
1R
0M
1]
0W
1h
0b
1r
0m
1>"
1I"
1T"
1^"
14
1:
1@
1F
1!"
1'"
1-"
13"
0"
b1 &
b1 (
b1 ,
b1 S
b1 ^
b1 i
b1 s
b1 v
b1 ?"
b1 J"
b1 U"
b1 _"
#55
1B
0/
0`
1y
0n
0d
1L"
b111 -
0I
00"
1Z"
1P"
1*
1D
b1111000 !
b1111000 )
b1000 w
15"
04
0:
0@
0G
0!"
0'"
0-"
02"
1"
#60
1+"
0?
0."
14
1:
1@
1G
1!"
1'"
1-"
12"
0"
#65
1<
00
0U
1z
0o
0c
0Y
1A"
b11 -
0C
0*"
1["
1O"
1E"
1>
b111100 !
b111100 )
b1100 w
1/"
04
0:
0A
0G
0!"
0'"
0,"
02"
1"
#70
1%"
09
0("
14
1:
1A
1G
1!"
1'"
1,"
12"
0"
#75
16
01
0K
1{
0e
0X
0O
17"
b1 -
0=
0$"
1Q"
1D"
1;"
18
b11110 !
b11110 )
b1110 w
1)"
04
0;
0A
0G
0!"
0&"
0,"
02"
1"
#80
1}
03
0""
14
1;
1A
1G
1!"
1&"
1,"
12"
0"
#85
14"
0x
0W"
0Z
0N
0u
b0 -
07
0|
1F"
1:"
12
b1111 !
b1111 )
b1111 w
1#"
05
0;
0A
0G
0~
0&"
0,"
02"
1"
#90
01"
15
1;
1A
1G
1~
1&"
1,"
12"
0"
#95
1."
0y
0L"
0Z"
0P"
0*
b111 !
b111 )
b111 w
05"
10"
05
0;
0A
0G
0~
0&"
0,"
03"
1"
#100
11"
1}
1%"
0."
04"
0""
0("
1y
1x
18"
1{
1B"
1z
1M"
1X"
1+"
1Q
0R
1\
0]
1g
0h
1q
0r
1="
0>"
07"
1H"
0I"
0A"
1S"
0T"
1]"
0^"
15
1;
1A
1G
1~
1&"
1,"
13"
0"
1#
b10 &
b10 (
b10 ,
b10 S
b10 ^
b10 i
b10 s
b10 v
b10 ?"
b10 J"
b10 U"
b10 _"
#105
11
1L
00"
1Z"
1P"
1*
b1111 !
b1111 )
b1111 w
15"
05
0;
0A
0G
0~
0&"
0,"
02"
1"
#110
13
06
15
1;
1A
1G
1~
1&"
1,"
12"
0"
#115
10
1V
02
1Z
1N
1u
b11111 !
b11111 )
b1 -
17
04
0;
0A
0G
0~
0&"
0,"
02"
1"
#120
19
0<
14
1;
1A
1G
1~
1&"
1,"
12"
0"
#125
1/
1a
08
1e
1X
1O
b111111 !
b111111 )
b11 -
1=
04
0:
0A
0G
0~
0&"
0,"
02"
1"
#130
1?
0B
14
1:
1A
1G
1~
1&"
1,"
12"
0"
#135
1.
1l
0>
1o
1c
1Y
b1111111 !
b1111111 )
b111 -
1C
04
0:
0@
0G
0~
0&"
0,"
02"
1"
#140
1E
0H
14
1:
1@
1G
1~
1&"
1,"
12"
0"
