Verilog_codes/8bitshiftregister/SISO/SR_SISO.v
module DFF(d,clk,reset,q);
input clk, reset;
input wire d;
output reg q;

always@(negedge clk or posedge reset)
begin
	if(reset)
 		q <= 1'b0;
	else
		q <= d;
end

endmodule



module SR_SISO(d,clk,reset,q);

input d, clk, reset;
output q;

wire w1, w2, w3;

DFF dff_1(d, clk, reset, w1);
DFF dff_2(w1, clk, reset, w2);
DFF dff_3(w2, clk, reset, w3);
DFF dff_4(w3, clk, reset, q);

endmodule




module SR_SISO_eight(d,clk,reset,q);

input d, clk, reset;
output q;

wire w1;

SR_SISO S1(d, clk, reset, w1);
SR_SISO S2(w1, clk, reset, q);

endmodule

Verilog_codes/8bitshiftregister/SR_SISO_tb.v
`include "SR_SISO.v"

module SR_SISO_tb;

reg clk, reset;
wire q;

reg inp;

initial
	begin
		$dumpfile("SR_SISO_tb.vcd");
		$dumpvars(0, SR_SISO_tb);
	end

SR_SISO_eight srsiso(inp, clk, reset, q);


initial
	begin
		inp = 0;
		reset=0;
		clk =0;
	end

always@(negedge clk)
	inp = ~inp;

always #5  
	clk =  ! clk; 

initial
	$monitor($time, ": clk=%b, rst=%b, inp=%b, q=%b\n", clk, reset, inp, q);

initial
	#100 $finish;

endmodule

Verilog_codes/8bitshiftregister/SISO/SR_SISO_tb.vcd
$date
	Tue Aug 25 15:04:38 2020
$end
$version
	Icarus Verilog
$end
$timescale
	1s
$end
$scope module SR_SISO_tb $end
$var wire 1 ! q $end
$var reg 1 " clk $end
$var reg 1 # inp $end
$var reg 1 $ reset $end
$scope module srsiso $end
$var wire 1 " clk $end
$var wire 1 # d $end
$var wire 1 $ reset $end
$var wire 1 % w1 $end
$var wire 1 ! q $end
$scope module S1 $end
$var wire 1 " clk $end
$var wire 1 # d $end
$var wire 1 $ reset $end
$var wire 1 & w3 $end
$var wire 1 ' w2 $end
$var wire 1 ( w1 $end
$var wire 1 % q $end
$scope module dff_1 $end
$var wire 1 " clk $end
$var wire 1 # d $end
$var wire 1 $ reset $end
$var reg 1 ( q $end
$upscope $end
$scope module dff_2 $end
$var wire 1 " clk $end
$var wire 1 ( d $end
$var wire 1 $ reset $end
$var reg 1 ' q $end
$upscope $end
$scope module dff_3 $end
$var wire 1 " clk $end
$var wire 1 ' d $end
$var wire 1 $ reset $end
$var reg 1 & q $end
$upscope $end
$scope module dff_4 $end
$var wire 1 " clk $end
$var wire 1 & d $end
$var wire 1 $ reset $end
$var reg 1 % q $end
$upscope $end
$upscope $end
$scope module S2 $end
$var wire 1 " clk $end
$var wire 1 % d $end
$var wire 1 $ reset $end
$var wire 1 ) w3 $end
$var wire 1 * w2 $end
$var wire 1 + w1 $end
$var wire 1 ! q $end
$scope module dff_1 $end
$var wire 1 " clk $end
$var wire 1 % d $end
$var wire 1 $ reset $end
$var reg 1 + q $end
$upscope $end
$scope module dff_2 $end
$var wire 1 " clk $end
$var wire 1 + d $end
$var wire 1 $ reset $end
$var reg 1 * q $end
$upscope $end
$scope module dff_3 $end
$var wire 1 " clk $end
$var wire 1 * d $end
$var wire 1 $ reset $end
$var reg 1 ) q $end
$upscope $end
$scope module dff_4 $end
$var wire 1 " clk $end
$var wire 1 ) d $end
$var wire 1 $ reset $end
$var reg 1 ! q $end
$upscope $end
$upscope $end
$upscope $end
$upscope $end
$enddefinitions $end
#0
$dumpvars
x+
x*
x)
0(
x'
x&
x%
0$
0#
0"
x!
$end
#5
1"
1#
#10
0'
0"
0#
#15
1"
1#
#20
0&
0"
0#
#25
1"
1#
#30
0%
0"
0#
#35
1"
1#
#40
0+
0"
0#
#45
1"
1#
#50
0*
0"
0#
#55
1"
1#
#60
0)
0"
0#
#65
1"
1#
#70
0!
0"
0#
#75
1"
1#
#80
0"
0#
#85
1"
1#
#90
0"
0#
#95
1"
1#
#100
0"
0#
#105
1"
1#
#110
0"
0#
#115
1"
1#
#120
0"
0#
#125
1"
1#
#130
0"
0#
#135
1"
1#
#140
0"
0#
#145
1"
1#
#150
0"
0#
#155
1"
1#
#160
0"
0#
#165
1"
1#
#170
0"
0#
#175
1"
1#
#180
0"
0#
#185
1"
1#
#190
0"
0#
#195
1"
1#
#200
0"
0#
