Verilog_codes/usr_8bit/usr.v
//D flip flop
module DFF(Q,D,clk);
	output Q;
	input D, clk;

	wire w0, w1, w2, w3, Q_bar;
	
	nand nand00(w0, w1, w3);
	nand nand01(w1, w0, clk);
	nand nand10(w2, w1, w3, clk);

	nand nand11(w3, w2, D);
	nand nand1_0(Q, w1, Q_bar);
	nand nand1_1(Q_bar, w2, Q);

endmodule

// a 4X1 MUX to perform operation according to user input, 00- do nothing, 01- right shift, 10- left shift, 11- parallel load;
module mux_4_1 (out, in0, in1, in2, in3, select);

	input in0,in1,in2,in3;
	input[1:0] select;
	output out;

	wire s0, s1, w0, w1, w2, w3;
	
	not n0(s0, select[0]);
	not n1(s1, select[1]);
	and and00(w0, s1, s0, in0);
	and and11(w1, s1, select[0], in1);
	and and22(w2, select[1], s0, in2);
	and and33(w3, select[1], select[0], in3);
	or out00(out, w0, w1, w2, w3);

endmodule 


//Universal shift register for 4 bits
module USR_4bit(out, pload, L_in, R_in, select, clk);


	output[3:0] out;
	input[3:0] pload;
	input L_in,R_in, clk;
	input[1:0] select;

	wire w0, w1, w2, w3;						

	DFF df3(out[3], w3, clk);
	DFF df2(out[2], w2, clk);
	DFF df1(out[1], w1, clk);
	DFF df0(out[0], w0, clk);

	mux_4_1 mx3(w3, out[3], R_in, out[2], pload[3], select);
	mux_4_1 mx2(w2, out[2], out[3], out[1], pload[2], select);
	mux_4_1 mx1(w1, out[1], out[2], out[0], pload[1], select);
	mux_4_1 mx0(w0, out[0], out[1], L_in,pload[0], select);

endmodule

//universal shift register in 8 bits using bottom up approach
module USR_8bit(out, pload, L_in, R_in, select, clk);


	output[7:0] out;
	input[7:0] pload;
	input L_in,R_in, clk;
	input[1:0] select;

	USR_4bit usr0(out[7:4], pload[7:4], out[3], R_in, select, clk);
	USR_4bit usr1(out[3:0], pload[3:0], L_in, out[4], select, clk);

endmodule

Verilog_codes/usr_8bit/usr_tb.v
`include "usr.v"

module top;

	wire[7:0] out;
	reg[7:0] pload;
	reg L_in, R_in, clk;
	reg[1:0] select;

	USR_8bit usr0(out, pload, L_in, R_in, select, clk);

	always #5 clk = ~clk;

	initial
	begin
		$monitor($time," select = %2b ..... pload = %8b ..... L_in = %b ..... R_in = %b ..... out = %8b", select, pload, L_in, R_in, out);
	end

	initial
	begin	
		clk =0;select = 2'b11; pload = 8'b0000_0000; L_in = 1'b0; R_in = 1'b0; 

		#10 select = 2'b11; pload = 8'b100_0001;

		#10 select = 2'b11; pload = 8'b1000_1110;

		#10 select = 2'b11; pload = 8'b1010_0101; 

		#10 select = 2'b01; R_in = 1'b1; 

		#10 select = 2'b01; R_in = 1'b0; 

		#10 select = 2'b01; R_in = 1'b0; 

		#10 select = 2'b01; R_in = 1'b0; 

		#10 select = 2'b01; R_in = 1'b0; 
		
		#10 select = 2'b00;

		#10 select = 2'b10; L_in = 1'b1;

		#10 select = 2'b10; L_in = 1'b1;

		#10 select = 2'b10; L_in = 1'b1;

		#10 select = 2'b10; L_in = 1'b0;

		#10 select = 2'b10; L_in = 1'b0;

	end
	
	initial
		#150 $finish;
	initial
	begin
	  $dumpfile("USR.vcd");      
      $dumpvars;
    end    
endmodule

Verilog_codes/usr_8bit/USR.vcd
$date
	Sun Aug 30 20:14:09 2020
$end
$version
	Icarus Verilog
$end
$timescale
	1s
$end
$scope module top $end
$var wire 8 ! out [7:0] $end
$var reg 1 " L_in $end
$var reg 1 # R_in $end
$var reg 1 $ clk $end
$var reg 8 % pload [7:0] $end
$var reg 2 & select [1:0] $end
$scope module usr0 $end
$var wire 1 ' L_in $end
$var wire 1 ( R_in $end
$var wire 1 ) clk $end
$var wire 8 * out [7:0] $end
$var wire 8 + pload [7:0] $end
$var wire 2 , select [1:0] $end
$scope module usr0 $end
$var wire 1 - L_in $end
$var wire 1 ( R_in $end
$var wire 1 ) clk $end
$var wire 4 . out [3:0] $end
$var wire 4 / pload [3:0] $end
$var wire 2 0 select [1:0] $end
$var wire 1 1 w0 $end
$var wire 1 2 w1 $end
$var wire 1 3 w2 $end
$var wire 1 4 w3 $end
$scope module df3 $end
$var wire 1 4 D $end
$var wire 1 5 Q $end
$var wire 1 6 Q_bar $end
$var wire 1 ) clk $end
$var wire 1 7 w0 $end
$var wire 1 8 w1 $end
$var wire 1 9 w2 $end
$var wire 1 : w3 $end
$upscope $end
$scope module df2 $end
$var wire 1 3 D $end
$var wire 1 ; Q $end
$var wire 1 < Q_bar $end
$var wire 1 ) clk $end
$var wire 1 = w0 $end
$var wire 1 > w1 $end
$var wire 1 ? w2 $end
$var wire 1 @ w3 $end
$upscope $end
$scope module df1 $end
$var wire 1 2 D $end
$var wire 1 A Q $end
$var wire 1 B Q_bar $end
$var wire 1 ) clk $end
$var wire 1 C w0 $end
$var wire 1 D w1 $end
$var wire 1 E w2 $end
$var wire 1 F w3 $end
$upscope $end
$scope module df0 $end
$var wire 1 1 D $end
$var wire 1 G Q $end
$var wire 1 H Q_bar $end
$var wire 1 ) clk $end
$var wire 1 I w0 $end
$var wire 1 J w1 $end
$var wire 1 K w2 $end
$var wire 1 L w3 $end
$upscope $end
$scope module mx3 $end
$var wire 1 M in0 $end
$var wire 1 ( in1 $end
$var wire 1 N in2 $end
$var wire 1 O in3 $end
$var wire 1 4 out $end
$var wire 1 P s0 $end
$var wire 1 Q s1 $end
$var wire 2 R select [1:0] $end
$var wire 1 S w0 $end
$var wire 1 T w1 $end
$var wire 1 U w2 $end
$var wire 1 V w3 $end
$upscope $end
$scope module mx2 $end
$var wire 1 W in0 $end
$var wire 1 X in1 $end
$var wire 1 Y in2 $end
$var wire 1 Z in3 $end
$var wire 1 3 out $end
$var wire 1 [ s0 $end
$var wire 1 \ s1 $end
$var wire 2 ] select [1:0] $end
$var wire 1 ^ w0 $end
$var wire 1 _ w1 $end
$var wire 1 ` w2 $end
$var wire 1 a w3 $end
$upscope $end
$scope module mx1 $end
$var wire 1 b in0 $end
$var wire 1 c in1 $end
$var wire 1 d in2 $end
$var wire 1 e in3 $end
$var wire 1 2 out $end
$var wire 1 f s0 $end
$var wire 1 g s1 $end
$var wire 2 h select [1:0] $end
$var wire 1 i w0 $end
$var wire 1 j w1 $end
$var wire 1 k w2 $end
$var wire 1 l w3 $end
$upscope $end
$scope module mx0 $end
$var wire 1 m in0 $end
$var wire 1 n in1 $end
$var wire 1 - in2 $end
$var wire 1 o in3 $end
$var wire 1 1 out $end
$var wire 1 p s0 $end
$var wire 1 q s1 $end
$var wire 2 r select [1:0] $end
$var wire 1 s w0 $end
$var wire 1 t w1 $end
$var wire 1 u w2 $end
$var wire 1 v w3 $end
$upscope $end
$upscope $end
$scope module usr1 $end
$var wire 1 ' L_in $end
$var wire 1 w R_in $end
$var wire 1 ) clk $end
$var wire 4 x out [3:0] $end
$var wire 4 y pload [3:0] $end
$var wire 2 z select [1:0] $end
$var wire 1 { w0 $end
$var wire 1 | w1 $end
$var wire 1 } w2 $end
$var wire 1 ~ w3 $end
$scope module df3 $end
$var wire 1 ~ D $end
$var wire 1 !" Q $end
$var wire 1 "" Q_bar $end
$var wire 1 ) clk $end
$var wire 1 #" w0 $end
$var wire 1 $" w1 $end
$var wire 1 %" w2 $end
$var wire 1 &" w3 $end
$upscope $end
$scope module df2 $end
$var wire 1 } D $end
$var wire 1 '" Q $end
$var wire 1 (" Q_bar $end
$var wire 1 ) clk $end
$var wire 1 )" w0 $end
$var wire 1 *" w1 $end
$var wire 1 +" w2 $end
$var wire 1 ," w3 $end
$upscope $end
$scope module df1 $end
$var wire 1 | D $end
$var wire 1 -" Q $end
$var wire 1 ." Q_bar $end
$var wire 1 ) clk $end
$var wire 1 /" w0 $end
$var wire 1 0" w1 $end
$var wire 1 1" w2 $end
$var wire 1 2" w3 $end
$upscope $end
$scope module df0 $end
$var wire 1 { D $end
$var wire 1 3" Q $end
$var wire 1 4" Q_bar $end
$var wire 1 ) clk $end
$var wire 1 5" w0 $end
$var wire 1 6" w1 $end
$var wire 1 7" w2 $end
$var wire 1 8" w3 $end
$upscope $end
$scope module mx3 $end
$var wire 1 9" in0 $end
$var wire 1 w in1 $end
$var wire 1 :" in2 $end
$var wire 1 ;" in3 $end
$var wire 1 ~ out $end
$var wire 1 <" s0 $end
$var wire 1 =" s1 $end
$var wire 2 >" select [1:0] $end
$var wire 1 ?" w0 $end
$var wire 1 @" w1 $end
$var wire 1 A" w2 $end
$var wire 1 B" w3 $end
$upscope $end
$scope module mx2 $end
$var wire 1 C" in0 $end
$var wire 1 D" in1 $end
$var wire 1 E" in2 $end
$var wire 1 F" in3 $end
$var wire 1 } out $end
$var wire 1 G" s0 $end
$var wire 1 H" s1 $end
$var wire 2 I" select [1:0] $end
$var wire 1 J" w0 $end
$var wire 1 K" w1 $end
$var wire 1 L" w2 $end
$var wire 1 M" w3 $end
$upscope $end
$scope module mx1 $end
$var wire 1 N" in0 $end
$var wire 1 O" in1 $end
$var wire 1 P" in2 $end
$var wire 1 Q" in3 $end
$var wire 1 | out $end
$var wire 1 R" s0 $end
$var wire 1 S" s1 $end
$var wire 2 T" select [1:0] $end
$var wire 1 U" w0 $end
$var wire 1 V" w1 $end
$var wire 1 W" w2 $end
$var wire 1 X" w3 $end
$upscope $end
$scope module mx0 $end
$var wire 1 Y" in0 $end
$var wire 1 Z" in1 $end
$var wire 1 ' in2 $end
$var wire 1 [" in3 $end
$var wire 1 { out $end
$var wire 1 \" s0 $end
$var wire 1 ]" s1 $end
$var wire 2 ^" select [1:0] $end
$var wire 1 _" w0 $end
$var wire 1 `" w1 $end
$var wire 1 a" w2 $end
$var wire 1 b" w3 $end
$upscope $end
$upscope $end
$upscope $end
$upscope $end
$enddefinitions $end
#0
$dumpvars
0b"
0a"
0`"
0_"
b11 ^"
0]"
0\"
0["
xZ"
xY"
0X"
0W"
0V"
0U"
b11 T"
0S"
0R"
0Q"
xP"
xO"
xN"
0M"
0L"
0K"
0J"
b11 I"
0H"
0G"
0F"
xE"
xD"
xC"
0B"
0A"
0@"
0?"
b11 >"
0="
0<"
0;"
x:"
x9"
18"
17"
16"
05"
x4"
x3"
12"
11"
10"
0/"
x."
x-"
1,"
1+"
1*"
0)"
x("
x'"
1&"
1%"
1$"
0#"
x""
x!"
0~
0}
0|
0{
b11 z
b0 y
bx x
xw
0v
0u
0t
0s
b11 r
0q
0p
0o
xn
xm
0l
0k
0j
0i
b11 h
0g
0f
0e
xd
xc
xb
0a
0`
0_
0^
b11 ]
0\
0[
0Z
xY
xX
xW
0V
0U
0T
0S
b11 R
0Q
0P
0O
xN
xM
1L
1K
1J
0I
xH
xG
1F
1E
1D
0C
xB
xA
1@
1?
1>
0=
x<
x;
1:
19
18
07
x6
x5
04
03
02
01
b11 0
b0 /
bx .
x-
b11 ,
b0 +
bx *
0)
0(
0'
b11 &
b0 %
0$
0#
0"
bx !
$end
#5
0M
0X
0N
0W
0c
0Y
0b
0n
0w
0d
0m
0-
09"
0D"
0:"
0C"
0O"
0E"
0N"
0Z"
0P"
0Y"
05
0;
0A
0G
b0 .
0!"
0'"
0-"
03"
b0 !
b0 *
b0 x
16
1<
1B
1H
1""
1("
1."
14"
09
0?
0E
0K
0%"
0+"
01"
07"
1$
1)
#10
1=
15"
0@
08"
13
1{
1a
1b"
1Z
1["
19
1?
1E
1K
1%"
1+"
11"
17"
b100 /
b1 y
0$
0)
b1000001 %
b1000001 +
#15
0<
1N
1W
1c
04"
1P"
1Y"
1;
b100 .
13"
b1000001 !
b1000001 *
b1 x
09
0>
0E
0K
0%"
0+"
01"
06"
1$
1)
#20
17
0=
1#"
1)"
1/"
05"
0:
1@
0&"
0,"
02"
18"
14
03
1~
1}
1|
0{
1V
0a
1B"
1M"
1X"
0b"
1O
0Z
1;"
1F"
1Q"
0["
19
1>
1E
1K
1%"
1+"
11"
16"
b1000 /
b1110 y
0$
0)
b10001110 %
b10001110 +
#25
0N
0W
0c
0P"
0Y"
06
1M
1X
0;
0""
1-
19"
1D"
0("
1:"
1C"
1O"
0."
1E"
1N"
1Z"
03"
15
b1000 .
1<
1!"
1'"
1-"
b10001110 !
b10001110 *
b1110 x
14"
08
0?
0E
0K
0$"
0*"
00"
07"
1$
1)
#30
1C
0#"
0/"
15"
0F
1&"
12"
08"
12
0~
0|
1{
1l
0B"
0X"
1b"
1e
0;"
0Q"
1["
18
1?
1E
1K
1$"
1*"
10"
17"
b1010 /
b101 y
0$
0)
b10100101 %
b10100101 +
#35
0-
09"
0D"
0E"
0N"
0Z"
0B
1Y
1b
1n
0!"
0-"
04"
1P"
1Y"
1A
b1010 .
1""
1."
13"
b10100101 !
b10100101 *
b101 x
08
0?
0D
0K
0%"
0*"
01"
06"
1$
1)
#40
1=
1I
1/"
17
0@
0C
0L
0)"
02"
05"
0:
13
1F
11
1,"
1|
18"
1T
14
1_
02
1t
0}
1V"
0{
1Q
0V
1\
1g
0l
1q
1="
1H"
0M"
1S"
1]"
0b"
18
1?
1D
1K
1%"
1*"
11"
16"
0$
0)
1#
1(
b1 &
b1 ,
b1 0
b1 R
b1 ]
b1 h
b1 r
b1 z
b1 >"
b1 I"
b1 T"
b1 ^"
#45
1L
12"
01
0|
12
0t
1~
0V"
1{
1j
0Y
0b
0n
1@"
0:"
0C"
0O"
1`"
0P"
0Y"
0<
1N
1W
1c
0A
0H
1w
1d
1m
0'"
0."
1E"
1N"
1Z"
03"
1;
1B
1G
b1101 .
1("
1-"
b11010010 !
b11010010 *
b10 x
14"
08
0>
0E
0J
0%"
0+"
00"
07"
1$
1)
#50
07
1C
1#"
15"
1:
0F
0I
0&"
0/"
08"
04
18
1>
1E
1J
1%"
1+"
10"
17"
0T
0$
0)
0#
0(
#55
1@
1&"
18"
03
0~
0{
0_
11
0@"
1}
0`"
0M
0X
1t
0w
0d
0m
1K"
0E"
0N"
0Z"
05
0B
1Y
1b
1n
0G
0""
1-
19"
1D"
0-"
04"
1P"
1Y"
16
1A
b110 .
1H
1!"
1."
13"
b1101001 !
b1101001 *
b1001 x
09
0>
0D
0K
0$"
0+"
01"
06"
1$
1)
#60
1I
1)"
0=
0L
0#"
0,"
05"
19
1>
1D
1K
1$"
1+"
11"
16"
0$
0)
#65
1F
1,"
02
0}
0j
1~
0K"
1|
0N
0W
0c
1@"
0-
09"
0D"
1V"
0P"
0Y"
0;
0H
1w
1d
1m
0!"
0("
1:"
1C"
1O"
03"
1<
1G
b11 .
1""
1'"
b110100 !
b110100 *
b100 x
14"
09
0?
0D
0J
0%"
0*"
01"
07"
1$
1)
#70
1#"
1/"
0C
0&"
0)"
02"
19
1?
1D
1J
1%"
1*"
11"
17"
0$
0)
#75
1L
12"
01
0|
0t
1}
0V"
1{
0Y
0b
0n
1K"
0:"
0C"
0O"
1`"
0A
b1 .
0""
1-
19"
1D"
0'"
0."
1E"
1N"
1Z"
1B
1!"
1("
1-"
b11010 !
b11010 *
b1010 x
09
0?
0E
0J
0$"
0+"
00"
07"
1$
1)
#80
1)"
15"
0I
0,"
0/"
08"
19
1?
1E
1J
1$"
1+"
10"
17"
0$
0)
#85
1&"
18"
0~
0{
0@"
1|
0`"
0w
0d
0m
1V"
0E"
0N"
0Z"
0G
b0 .
0("
1:"
1C"
1O"
0-"
04"
1P"
1Y"
1H
1'"
1."
13"
b1101 !
b1101 *
b1101 x
09
0?
0E
0K
0$"
0*"
01"
06"
1$
1)
#90
0&"
1)"
08"
1~
0,"
1{
0/"
1?"
1J"
1}
0|
1_"
1#"
12"
15"
1P
1[
1f
1p
1<"
1G"
0K"
1R"
0V"
1\"
19
1?
1E
1K
1$"
1*"
11"
16"
0$
0)
b0 &
b0 ,
b0 0
b0 R
b0 ]
b0 h
b0 r
b0 z
b0 >"
b0 I"
b0 T"
b0 ^"
#95
09
0?
0E
0K
0$"
0*"
01"
06"
1$
1)
#100
0)"
1I
1,"
1/"
0L
0}
02"
11
0?"
0J"
1|
0_"
0Q
0\
0g
0q
1u
0="
1A"
0H"
0S"
1W"
0]"
19
1?
1E
1K
1$"
1*"
11"
16"
1a"
0$
0)
1"
1'
b10 &
b10 ,
b10 0
b10 R
b10 ]
b10 h
b10 r
b10 z
b10 >"
b10 I"
b10 T"
b10 ^"
#105
1&"
0~
12
0A"
1}
1k
0:"
0C"
0O"
1L"
0H
1w
1d
1m
0'"
0."
1E"
1N"
1Z"
1G
b1 .
1("
1-"
b11011 !
b11011 *
b1011 x
09
0?
0E
0J
0$"
0+"
00"
06"
1$
1)
#110
1C
1)"
0F
0#"
0,"
19
1?
1E
1J
1$"
1+"
10"
16"
0$
0)
#115
1L
01
13
0u
1~
1`
0-
09"
0D"
1A"
0B
1Y
1b
1n
0!"
0("
1:"
1C"
1O"
1A
b11 .
1""
1'"
b110111 !
b110111 *
b111 x
09
0?
0D
0J
0%"
0*"
00"
06"
1$
1)
#120
1=
1#"
0@
0I
0&"
19
1?
1D
1J
1%"
1*"
10"
16"
0$
0)
#125
1F
02
14
0k
11
1U
0w
0d
0m
1u
0<
1N
1W
1c
0G
0""
1-
19"
1D"
1;
b110 .
1H
1!"
b1101111 !
b1101111 *
b1111 x
09
0>
0D
0K
0$"
0*"
00"
06"
1$
1)
#130
05"
17
1I
18"
0:
0C
0L
0{
19
1>
1D
1K
1$"
1*"
10"
16"
0a"
0$
0)
0"
0'
#135
1@
12"
03
0|
0`
12
0W"
0Y
0b
0n
1k
0P"
0Y"
06
1M
1X
0A
0H
1w
1d
1m
03"
b1110 x
15
1B
1G
b11011110 !
b11011110 *
b1101 .
14"
08
0>
0E
0J
0$"
0*"
00"
07"
1$
1)
#140
1C
0=
0F
0/"
18
1>
1E
1J
1$"
1*"
10"
17"
0$
0)
#145
1:
1,"
04
0}
0U
13
0L"
0N
0W
0c
1`
0E"
0N"
0Z"
0;
0B
1Y
1b
1n
0-"
b1100 x
1<
1A
b10111100 !
b10111100 *
b1011 .
1."
08
0?
0D
0J
0$"
0*"
01"
07"
1$
1)
#150
1=
07
0@
0)"
18
1?
1D
1J
1$"
1*"
11"
17"
0$
0)
